Metadata-Version: 2.1
Name: py2crypt
Version: 1.0
Summary: This library provides a top-level interface to the cryptography.io module.
Home-page: https://github.com/badlock/py2crypt
Author: Badlock
License: MIT
Platform: UNKNOWN
License-File: LICENSE
